milea_helpdesk/__init__.py
milea_helpdesk/admin.py
milea_helpdesk/apps.py
milea_helpdesk/models.py
milea_helpdesk/settings.py
milea_helpdesk/tests.py
milea_helpdesk/views.py
milea_helpdesk/migrations/__init__.py
milea_helpdesk/migrations/__pycache__/__init__.cpython-311.pyc
milea_helpdesk-0.2.dist-info/METADATA
milea_helpdesk-0.2.dist-info/WHEEL
milea_helpdesk-0.2.dist-info/top_level.txt
milea_helpdesk-0.2.dist-info/RECORD
