Metadata-Version: 2.1
Name: milea-helpdesk
Version: 0.2
Summary: Milea Framework - Milea Helpdesk Module
Author: red-pepper-services
Author-email: pypi@schiegg.at
License: MIT
Requires-Dist: milea-base >=0.1
